ppg/__init__.py
ppg/__main__.py
ppg/_aws.py
ppg/_gpg.py
ppg/_server.py
ppg/_state.py
ppg/cmdline.py
ppg/resources.py
ppg/upload.py
ppg/_defaults/requirements/arch.txt
ppg/_defaults/requirements/base.txt
ppg/_defaults/requirements/fedora.txt
ppg/_defaults/requirements/linux.txt
ppg/_defaults/requirements/ubuntu.txt
ppg/_defaults/src/build/docker/arch/.bashrc
ppg/_defaults/src/build/docker/arch/Dockerfile
ppg/_defaults/src/build/docker/arch/gpg-agent.conf
ppg/_defaults/src/build/docker/arch/motd
ppg/_defaults/src/build/docker/fedora/.bashrc
ppg/_defaults/src/build/docker/fedora/.rpmmacros
ppg/_defaults/src/build/docker/fedora/Dockerfile
ppg/_defaults/src/build/docker/fedora/gpg-agent.conf
ppg/_defaults/src/build/docker/fedora/motd
ppg/_defaults/src/build/docker/ubuntu/.bashrc
ppg/_defaults/src/build/docker/ubuntu/Dockerfile
ppg/_defaults/src/build/docker/ubuntu/gpg-agent.conf
ppg/_defaults/src/build/docker/ubuntu/gpg.conf
ppg/_defaults/src/build/docker/ubuntu/motd
ppg/_defaults/src/build/settings/arch.json
ppg/_defaults/src/build/settings/base.json
ppg/_defaults/src/build/settings/fedora.json
ppg/_defaults/src/build/settings/linux.json
ppg/_defaults/src/build/settings/mac.json
ppg/_defaults/src/build/settings/release.json
ppg/_defaults/src/build/settings/ubuntu.json
ppg/_defaults/src/build/settings/windows.json
ppg/_defaults/src/freeze/mac/Contents/Info.plist
ppg/_defaults/src/freeze/windows/version_info.py
ppg/_defaults/src/installer/linux/usr/share/applications/AppName.desktop
ppg/_defaults/src/installer/windows/Installer.nsi
ppg/_defaults/src/repo/fedora/AppName.repo
ppg/_defaults/src/repo/ubuntu/distributions
ppg/builtin_commands/__init__.py
ppg/builtin_commands/_account.py
ppg/builtin_commands/_docker.py
ppg/builtin_commands/_licensing.py
ppg/builtin_commands/_util.py
ppg/builtin_commands/components.py
ppg/builtin_commands/package.json
ppg/builtin_commands/_gpg/Dockerfile
ppg/builtin_commands/_gpg/__init__.py
ppg/builtin_commands/_gpg/genkey.sh
ppg-1.2.0.dist-info/licenses/LICENSE
ppg-1.2.0.dist-info/licenses/NOTICE
ppg-1.2.0.dist-info/METADATA
ppg-1.2.0.dist-info/WHEEL
ppg-1.2.0.dist-info/entry_points.txt
ppg-1.2.0.dist-info/top_level.txt
ppg-1.2.0.dist-info/RECORD
