Metadata-Version: 2.4
Name: ppg
Version: 1.2.0
Summary: PPG: A powerful app generator simplifying development with Python and Qt.
Home-page: https://ppg.neuri.ai
Author: Neuri
Author-email: alfredo@neuri.ai
License: GPL-3.0-only
Keywords: ppg,python,pyqt,pyside,desktop,application,generator,cli,component,state management,pydux,fbs,react,redux,app development,modular,scalable,lifecycle,component-based,pyside6,pyqt6,pyqt5,pyqt6 generator,pyqt5 generator,pyside6 generator,pyside5 generator,pyqt6 app,pyqt5 app,pyside6 app,pyside5 app,app generator,redux
Platform: MacOS
Platform: Windows
Platform: Debian
Platform: Fedora
Platform: CentOS
Platform: Arch
Platform: Raspbian
Classifier: Intended Audience :: Developers
Classifier: License :: OSI Approved :: GNU General Public License v3 or later (GPLv3+)
Classifier: Operating System :: OS Independent
Classifier: Topic :: Software Development :: Libraries
Classifier: Topic :: Software Development :: Libraries :: Python Modules
Classifier: Programming Language :: Python :: 3.8
Classifier: Programming Language :: Python :: 3.9
Classifier: Programming Language :: Python :: 3.10
Classifier: Programming Language :: Python :: 3.11
Classifier: Programming Language :: Python :: 3.12
License-File: LICENSE
License-File: NOTICE
Requires-Dist: PyInstaller>=6.9.0
Requires-Dist: pydantic>=2.11.7
Requires-Dist: questionary==2.1.0
Requires-Dist: rich==14.1.0
Requires-Dist: watchdog==6.0.0
Requires-Dist: astor==0.8.1
Requires-Dist: prompt_toolkit==3.0.39
Provides-Extra: licensing
Requires-Dist: rsa>=3.4.2; extra == "licensing"
Provides-Extra: sentry
Requires-Dist: sentry-sdk>=0.6.6; extra == "sentry"
Provides-Extra: upload
Requires-Dist: boto3; extra == "upload"
Dynamic: author
Dynamic: author-email
Dynamic: classifier
Dynamic: description
Dynamic: description-content-type
Dynamic: home-page
Dynamic: keywords
Dynamic: license
Dynamic: license-file
Dynamic: platform
Dynamic: provides-extra
Dynamic: requires-dist
Dynamic: summary
